Metadata-Version: 2.1
Name: whatsapp-parse
Version: 0.2.2
Summary: A parsing library for WhatsApp chat logs
Home-page: https://github.com/HassnHamada/whatsapp-chat-parser.git
Author: Hassn Hamada
Author-email: hassneltokhy4@gmail.com
License: MIT
License-File: LICENSE
Requires-Dist: pandas
